maivi/__init__.py
maivi/__main__.py
maivi/cli/__init__.py
maivi/cli/cli.py
maivi/cli/server.py
maivi/cli/terminal_ui.py
maivi/core/__init__.py
maivi/core/chunk_merger.py
maivi/core/pause_detector.py
maivi/core/streaming_recorder.py
maivi/gui/__init__.py
maivi/gui/qt_gui.py
maivi/utils/__init__.py
maivi/utils/macos_permissions.py
maivi-0.4.0.dist-info/licenses/LICENSE
maivi-0.4.0.dist-info/METADATA
maivi-0.4.0.dist-info/WHEEL
maivi-0.4.0.dist-info/entry_points.txt
maivi-0.4.0.dist-info/top_level.txt
maivi-0.4.0.dist-info/RECORD
