Metadata-Version: 2.4
Name: maivi
Version: 0.4.0
Summary: Maivi - My AI Voice Input: Real-time voice-to-text with hotkey support
Author: Maxime Rivest
License: MIT
Project-URL: Homepage, https://github.com/MaximeRivest/maivi
Project-URL: Repository, https://github.com/MaximeRivest/maivi
Project-URL: Issues, https://github.com/MaximeRivest/maivi/issues
Keywords: speech-to-text,voice,transcription,ai,nemo
Classifier: Development Status :: 4 - Beta
Classifier: Intended Audience :: Developers
Classifier: Intended Audience :: End Users/Desktop
Classifier: License :: OSI Approved :: MIT License
Classifier: Operating System :: OS Independent
Classifier: Programming Language :: Python :: 3
Classifier: Programming Language :: Python :: 3.10
Classifier: Programming Language :: Python :: 3.11
Classifier: Programming Language :: Python :: 3.12
Classifier: Topic :: Multimedia :: Sound/Audio :: Speech
Classifier: Topic :: Scientific/Engineering :: Artificial Intelligence
Requires-Python: <3.13,>=3.10
License-File: LICENSE
Requires-Dist: nemo-toolkit[asr]>=2.0.0
Requires-Dist: PySide6>=6.5.0
Requires-Dist: sounddevice>=0.4.6
Requires-Dist: soundfile>=0.12.0
Requires-Dist: librosa>=0.10.0
Requires-Dist: numpy<2.0.0,>=1.24.0
Requires-Dist: pynput>=1.7.6
Requires-Dist: pyperclip>=1.8.2
Requires-Dist: plyer>=2.1.0
Requires-Dist: torch>=2.0.0
Requires-Dist: torchaudio>=2.0.0
Requires-Dist: ml-dtypes<0.6.0,>=0.5.0
Requires-Dist: platformdirs>=3.0.0
Provides-Extra: dev
Requires-Dist: pytest>=7.0; extra == "dev"
Requires-Dist: pytest-cov>=4.0; extra == "dev"
Requires-Dist: black>=23.0; extra == "dev"
Requires-Dist: isort>=5.12; extra == "dev"
Requires-Dist: flake8>=6.0; extra == "dev"
Provides-Extra: build
Requires-Dist: pyinstaller>=5.0; extra == "build"
Requires-Dist: build>=0.10; extra == "build"
Requires-Dist: twine>=4.0; extra == "build"
Dynamic: license-file
